CHANGES
LICENSE
MANIFEST.in
README
setup.cfg
setup.py
FileCatalog.egg-info/PKG-INFO
FileCatalog.egg-info/SOURCES.txt
FileCatalog.egg-info/dependency_links.txt
FileCatalog.egg-info/not-zip-safe
FileCatalog.egg-info/requires.txt
FileCatalog.egg-info/top_level.txt
filecatalog/__init__.py
filecatalog/indexer.py
filecatalog/io.py
filecatalog/viewer.py
filecatalog/xhtmlizer.py