Metadata-Version: 1.0
Name: FileCatalog
Version: 0.3.1
Summary: Tools to create, view and transform hierachical YAML representations of directory structures.
Home-page: http://homework.nwsnet.de/
Author: Jochen Kupperschmidt
Author-email: homework at nwsnet dot de
License: GPL <http://www.opensource.org/licenses/gpl-license.php>
Platform: UNKNOWN
Classifier: Environment :: Console
Classifier: Intended Audience :: End Users/Desktop
Classifier: License :: OSI Approved :: GNU General Public License (GPL)
Classifier: Natural Language :: English
Classifier: Operating System :: OS Independent
Classifier: Programming Language :: Python
Classifier: Topic :: System :: Archiving
Classifier: Topic :: Utilities
